pasync/__init__.py
pasync/event_loop.py
pasync/promise/__init__.py
pasync/runner/__init__.py
pasync/task.py
pasync-0.3.1.dist-info/LICENSE
pasync-0.3.1.dist-info/METADATA
pasync-0.3.1.dist-info/WHEEL
pasync-0.3.1.dist-info/RECORD
