Metadata-Version: 2.1
Name: pasync
Version: 0.3.1
Summary: An event loop for python async
Author: Huy-DNA
Author-email: huydo862003@gmail.com
Requires-Python: >=3.10,<4.0
Classifier: Programming Language :: Python :: 3
Classifier: Programming Language :: Python :: 3.10
Classifier: Programming Language :: Python :: 3.11
Classifier: Programming Language :: Python :: 3.12
